git_migrate/.gitmigrate.dist
git_migrate/__init__.py
git_migrate/cli.py
git_migrate-0.3.1.dist-info/DESCRIPTION.rst
git_migrate-0.3.1.dist-info/METADATA
git_migrate-0.3.1.dist-info/RECORD
git_migrate-0.3.1.dist-info/WHEEL
git_migrate-0.3.1.dist-info/entry_points.txt
git_migrate-0.3.1.dist-info/metadata.json
git_migrate-0.3.1.dist-info/top_level.txt
