Metadata-Version: 2.0
Name: git-migrate
Version: 0.3.1
Summary: Execute commands from shell file, storing last successful execution in detached git branch.
Home-page: https://github.com/garex/git-migrate
Author: Alexander Ustimenko
Author-email: a@ustimen.co
License: MIT
Keywords: git migrate shell script
Platform: UNKNOWN
Classifier: Development Status :: 3 - Alpha
Classifier: Environment :: Console
Classifier: Intended Audience :: System Administrators
Classifier: License :: OSI Approved :: MIT License
Classifier: Operating System :: OS Independent
Classifier: Programming Language :: Python :: 2.7
Classifier: Topic :: System :: Installation/Setup
Classifier: Topic :: System :: Software Distribution
Classifier: Topic :: Utilities
Requires-Dist: colorama
